setup.py
mbd_formatter/formater.py
mbd_formatter.egg-info/PKG-INFO
mbd_formatter.egg-info/SOURCES.txt
mbd_formatter.egg-info/dependency_links.txt
mbd_formatter.egg-info/requires.txt
mbd_formatter.egg-info/top_level.txt