Metadata-Version: 2.1
Name: mbd-formatter
Version: 1.0.0
Summary: a formater for print
Author: maberdeb
Author-email: maxime@maberdeb.com
